kui/__init__.py
kui/__version__.py
kui/asgi/__init__.py
kui/asgi/applications.py
kui/asgi/background.py
kui/asgi/cors.py
kui/asgi/exceptions.py
kui/asgi/lifespan.py
kui/asgi/openapi.py
kui/asgi/parameters.py
kui/asgi/requests.py
kui/asgi/responses.py
kui/asgi/routing.py
kui/asgi/templates.py
kui/asgi/views.py
kui/cors.py
kui/exceptions.py
kui/openapi/__init__.py
kui/openapi/application.py
kui/openapi/extra_docs.py
kui/openapi/schema.py
kui/openapi/specification.py
kui/openapi/templates/rapidoc.html
kui/openapi/templates/redoc.html
kui/openapi/templates/swagger.html
kui/openapi/types.py
kui/parameters/__init__.py
kui/parameters/field_functions.py
kui/parameters/fields.py
kui/py.typed
kui/pydantic_compatible.py
kui/responses.py
kui/routing/__init__.py
kui/routing/__main__.py
kui/routing/commands.py
kui/routing/extensions/__init__.py
kui/routing/extensions/file.py
kui/routing/extensions/multimethod.py
kui/routing/routers.py
kui/routing/routes.py
kui/routing/tree.py
kui/routing/typing.py
kui/security.py
kui/status.py
kui/templates.py
kui/utils/__init__.py
kui/utils/contextvars.py
kui/utils/importer.py
kui/utils/inspect.py
kui/utils/objects.py
kui/utils/pipe.py
kui/utils/state.py
kui/wsgi/__init__.py
kui/wsgi/applications.py
kui/wsgi/background.py
kui/wsgi/cors.py
kui/wsgi/exceptions.py
kui/wsgi/openapi.py
kui/wsgi/parameters.py
kui/wsgi/requests.py
kui/wsgi/responses.py
kui/wsgi/routing.py
kui/wsgi/templates.py
kui/wsgi/views.py
kui-1.14.0.dist-info/WHEEL
kui-1.14.0.dist-info/METADATA
kui-1.14.0.dist-info/licenses/LICENSE
kui-1.14.0.dist-info/RECORD
