Metadata-Version: 2.1
Name: kui
Version: 1.14.0
Summary: An easy-to-use web framework.
License: Apache-2.0
Author-email: abersheeran <me@abersheeran.com>
Requires-Python: >=3.9,<4.0
Classifier: License :: OSI Approved :: Apache Software License
Classifier: Programming Language :: Python :: 3
Classifier: Programming Language :: Python :: Implementation :: CPython
Requires-Dist: baize>=0.22.0
Requires-Dist: pydantic>=2
Requires-Dist: typing-extensions>=4.2.0
Project-URL: documentation, https://kui.aber.sh
Project-URL: homepage, https://github.com/abersheeran/kui
Project-URL: repository, https://github.com/abersheeran/kui
